{
  "video_id": "7535948734648110350",
  "title": "Replying to @ianisfun #spirituality #ego #source #soul #identity ",
  "tags": [
    {
      "tag": "think spiritual",
      "score": 0.4875,
      "type": "keyphrase"
    },
    {
      "tag": "difference ego",
      "score": 0.4978,
      "type": "keyphrase"
    },
    {
      "tag": "essentially think spiritual",
      "score": 0.499,
      "type": "keyphrase"
    },
    {
      "tag": "life ego",
      "score": 0.5002,
      "type": "keyphrase"
    },
    {
      "tag": "ego distinctly confirmation",
      "score": 0.5059,
      "type": "keyphrase"
    },
    {
      "tag": "ego personality fundamental",
      "score": 0.5085,
      "type": "keyphrase"
    },
    {
      "tag": "ego essence",
      "score": 0.5176,
      "type": "keyphrase"
    },
    {
      "tag": "difference ego identity",
      "score": 0.5183,
      "type": "keyphrase"
    },
    {
      "tag": "universe universe ego",
      "score": 0.5298,
      "type": "keyphrase"
    },
    {
      "tag": "universe ego",
      "score": 0.5437,
      "type": "keyphrase"
    }
  ],
  "extracted_at": "2025-10-22T17:55:53.200871"
}