{
  "video_id": "7530738286935952670",
  "title": "Transmission VI: The Paradox of Pre-Existence #truth #esoteric #parad...",
  "tags": [
    {
      "tag": "fate energy potential",
      "score": 0.4256,
      "type": "keyphrase"
    },
    {
      "tag": "feeling free",
      "score": 0.4259,
      "type": "keyphrase"
    },
    {
      "tag": "choice arises aware",
      "score": 0.4279,
      "type": "keyphrase"
    },
    {
      "tag": "consciousness",
      "score": 0.4307,
      "type": "keyphrase"
    },
    {
      "tag": "future using aliveness",
      "score": 0.4339,
      "type": "keyphrase"
    },
    {
      "tag": "pathways laid fate",
      "score": 0.438,
      "type": "keyphrase"
    },
    {
      "tag": "predestination old",
      "score": 0.4405,
      "type": "keyphrase"
    },
    {
      "tag": "isn predestination",
      "score": 0.4716,
      "type": "keyphrase"
    },
    {
      "tag": "spontaneity choice feeling",
      "score": 0.473,
      "type": "keyphrase"
    },
    {
      "tag": "spontaneous choices actually",
      "score": 0.4906,
      "type": "keyphrase"
    }
  ],
  "extracted_at": "2025-10-23T12:05:16.020215"
}